dwalk/VERSION
dwalk/__init__.py
dwalk/__main__.py
dwalk/cli.py
dwalk/directories.py
dwalk/dwalk.py
dwalk/merge.py
dwalk/py.typed
dwalk/test_cli.py
dwalk/test_directories.py
dwalk/test_dwalk.py
dwalk/test_merge.py
dwalk/test_version.py
dwalk/version.py
dwalk-1.1.0.dist-info/LICENSE
dwalk-1.1.0.dist-info/METADATA
dwalk-1.1.0.dist-info/WHEEL
dwalk-1.1.0.dist-info/entry_points.txt
dwalk-1.1.0.dist-info/top_level.txt
dwalk-1.1.0.dist-info/RECORD
