Metadata-Version: 2.1
Name: dwalk
Version: 1.1.0
Summary: Walks directories and merges dictionaries
Home-page: https://github.com/cariad/dwalk
Author: Cariad Eccleston
Author-email: cariad@cariad.me
License: MIT License
Platform: UNKNOWN
Classifier: Development Status :: 5 - Production/Stable
Classifier: Environment :: Console
Classifier: Intended Audience :: Developers
Classifier: License :: OSI Approved :: MIT License
Classifier: Natural Language :: English
Classifier: Operating System :: OS Independent
Classifier: Programming Language :: Python :: 3 :: Only
Classifier: Programming Language :: Python :: 3.8
Classifier: Programming Language :: Python :: 3.9
Classifier: Topic :: Software Development
Classifier: Topic :: Utilities
Requires-Python: >=3.8
Requires-Dist: ruamel.yaml (~=0.16)
